armonik_analytics/__init__.py
armonik_analytics/_version.py
armonik_analytics/stats.py
armonik_analytics/utils.py
armonik_analytics/metrics/__init__.py
armonik_analytics/metrics/base.py
armonik_analytics/metrics/common.py
armonik_analytics/metrics/time_series.py
armonik_analytics/metrics/transitions.py
armonik_analytics-0.0.2.dist-info/LICENSE
armonik_analytics-0.0.2.dist-info/METADATA
armonik_analytics-0.0.2.dist-info/WHEEL
armonik_analytics-0.0.2.dist-info/top_level.txt
armonik_analytics-0.0.2.dist-info/RECORD
