Metadata-Version: 2.1
Name: armonik_analytics
Version: 0.0.2
Summary: Set of tools for analyzing workload execution on ArmoniK.
License: Apache Software License 2.0
Project-URL: Homepage, https://github.com/aneoconsulting/ArmoniK.Analytics
Project-URL: repository, https://github.com/aneoconsulting/ArmoniK.Analytics
Project-URL: Bug Tracker, https://github.com/aneoconsulting/ArmoniK.Analytics/issues
Keywords: ArmoniK,Analytics,task graph,HPC
Classifier: Programming Language :: Python :: 3
Requires-Python: >=3.10
License-File: LICENSE
Requires-Dist: armonik >=3.16.1
Requires-Dist: numpy
Provides-Extra: dev
Requires-Dist: mypy ; extra == 'dev'
Requires-Dist: ruff ; extra == 'dev'
Provides-Extra: samples
Requires-Dist: matplotlib ; extra == 'samples'
Provides-Extra: tests
Requires-Dist: coverage ; extra == 'tests'
Requires-Dist: pytest ; extra == 'tests'
Requires-Dist: pytest-cov ; extra == 'tests'
Requires-Dist: pytest-benchmark[histogram] ; extra == 'tests'
